LICENSE
MANIFEST.in
README.rst
setup.py
py_sparkblocks.egg-info/PKG-INFO
py_sparkblocks.egg-info/SOURCES.txt
py_sparkblocks.egg-info/dependency_links.txt
py_sparkblocks.egg-info/top_level.txt
sparkblocks/__init__.py