Metadata-Version: 1.0
Name: py-sparkblocks
Version: 1.0.1
Summary: Util for generating unicode text based sparkline bargraphs from lists of numbers
Home-page: https://github.com/1stvamp/py-sparkblocks
Author: Wes Mason
Author-email: wes@1stvamp.org
License: BSD
Platform: UNKNOWN
